pgscatalog/utils/__init__.py
pgscatalog_utils-2.0.2.dist-info/licenses/LICENSE
pgscatalog_utils-2.0.2.dist-info/METADATA
pgscatalog_utils-2.0.2.dist-info/WHEEL
pgscatalog_utils-2.0.2.dist-info/top_level.txt
pgscatalog_utils-2.0.2.dist-info/RECORD
